efb_fb_messenger_slave/__init__.py
efb_fb_messenger_slave/__main__.py
efb_fb_messenger_slave/__version__.py
efb_fb_messenger_slave/efms_chat.py
efb_fb_messenger_slave/efms_client.py
efb_fb_messenger_slave/extra_functions.py
efb_fb_messenger_slave/master_messages.py
efb_fb_messenger_slave/utils.py
efb_fb_messenger_slave/wizard.py
efb_fb_messenger_slave/locale/az_AZ/LC_MESSAGES/efb_fb_messenger_slave.mo
efb_fb_messenger_slave/locale/az_AZ/LC_MESSAGES/efb_fb_messenger_slave.po
efb_fb_messenger_slave/locale/en_US/LC_MESSAGES/efb_fb_messenger_slave.mo
efb_fb_messenger_slave/locale/en_US/LC_MESSAGES/efb_fb_messenger_slave.po
efb_fb_messenger_slave/locale/es_AR/LC_MESSAGES/efb_fb_messenger_slave.mo
efb_fb_messenger_slave/locale/es_AR/LC_MESSAGES/efb_fb_messenger_slave.po
efb_fb_messenger_slave/locale/es_VE/LC_MESSAGES/efb_fb_messenger_slave.mo
efb_fb_messenger_slave/locale/es_VE/LC_MESSAGES/efb_fb_messenger_slave.po
efb_fb_messenger_slave/locale/id_ID/LC_MESSAGES/efb_fb_messenger_slave.mo
efb_fb_messenger_slave/locale/id_ID/LC_MESSAGES/efb_fb_messenger_slave.po
efb_fb_messenger_slave/locale/it_IT/LC_MESSAGES/efb_fb_messenger_slave.mo
efb_fb_messenger_slave/locale/it_IT/LC_MESSAGES/efb_fb_messenger_slave.po
efb_fb_messenger_slave/locale/ja_JP/LC_MESSAGES/efb_fb_messenger_slave.mo
efb_fb_messenger_slave/locale/ja_JP/LC_MESSAGES/efb_fb_messenger_slave.po
efb_fb_messenger_slave/locale/ms_MY/LC_MESSAGES/efb_fb_messenger_slave.mo
efb_fb_messenger_slave/locale/ms_MY/LC_MESSAGES/efb_fb_messenger_slave.po
efb_fb_messenger_slave/locale/ro_RO/LC_MESSAGES/efb_fb_messenger_slave.mo
efb_fb_messenger_slave/locale/ro_RO/LC_MESSAGES/efb_fb_messenger_slave.po
efb_fb_messenger_slave/locale/tr_TR/LC_MESSAGES/efb_fb_messenger_slave.mo
efb_fb_messenger_slave/locale/tr_TR/LC_MESSAGES/efb_fb_messenger_slave.po
efb_fb_messenger_slave/locale/zh_CN/LC_MESSAGES/efb_fb_messenger_slave.mo
efb_fb_messenger_slave/locale/zh_CN/LC_MESSAGES/efb_fb_messenger_slave.po
efb_fb_messenger_slave-2.0.0b21.dist-info/LICENSE.md
efb_fb_messenger_slave-2.0.0b21.dist-info/METADATA
efb_fb_messenger_slave-2.0.0b21.dist-info/WHEEL
efb_fb_messenger_slave-2.0.0b21.dist-info/entry_points.txt
efb_fb_messenger_slave-2.0.0b21.dist-info/top_level.txt
efb_fb_messenger_slave-2.0.0b21.dist-info/RECORD
