Metadata-Version: 2.1
Name: efb-fb-messenger-slave
Version: 2.0.0b21
Summary: Facebook Messenger Slave Channel for EH Forwarder Bot, based on ``fbchat``.
Home-page: https://efms.1a23.studio
Author: Eana Hufwe
Author-email: ilove@1a23.com
License: AGPLv3+
Keywords: ehforwarderbot,EH Forwarder Bot,EH Forwarder Bot Master Channel,facebook messenger,messenger,chatbot
Platform: UNKNOWN
Classifier: Development Status :: 4 - Beta
Classifier: License :: OSI Approved :: GNU Affero General Public License v3 or later (AGPLv3+)
Classifier: Intended Audience :: Developers
Classifier: Intended Audience :: End Users/Desktop
Classifier: Programming Language :: Python :: 3 :: Only
Classifier: Programming Language :: Python :: 3.6
Classifier: Programming Language :: Python :: 3.7
Classifier: Topic :: Communications :: Chat
Classifier: Topic :: Utilities
Requires-Python: >=3.6
Requires-Dist: ehforwarderbot (>=2.0.0b28)
Requires-Dist: fbchat (~=1.9)
Requires-Dist: PyYaml (>=5.3)
Requires-Dist: requests
Requires-Dist: emoji
Requires-Dist: bullet
Requires-Dist: cjkwrap
